spotifyy/__init__.py
spotifyy/extensions.py
spotifyy/sessions.py
spotifyy-0.1.1.dist-info/LICENSE.txt
spotifyy-0.1.1.dist-info/METADATA
spotifyy-0.1.1.dist-info/WHEEL
spotifyy-0.1.1.dist-info/top_level.txt
spotifyy-0.1.1.dist-info/RECORD
