Metadata-Version: 2.1
Name: spotifyy
Version: 0.1.1
Summary: Spotify interface used by Spotbot
Home-page: https://github.com/JesperK123456/spotifyy
Author: Saltpile123
Author-email: ikhoudvanberichten@gmail.com
License: UNKNOWN
Platform: UNKNOWN
Classifier: Programming Language :: Python :: 3
Requires-Python: >=3.6
